powerhouse_assistant/__init__.py
powerhouse_assistant/__main__.py
powerhouse_assistant/AddressBook/Address_Book_Handler.py
powerhouse_assistant/AddressBook/address_saves/address_book.log
powerhouse_assistant/AddressBook/address_saves/address_book_auto_save.bin
powerhouse_assistant/AddressBook/addressbook.py
powerhouse_assistant/AddressBook/addressbook_data.py
powerhouse_assistant/GameGooseKiller/font/UA Propisi.ttf
powerhouse_assistant/GameGooseKiller/Game_goose.py
powerhouse_assistant/GameGooseKiller/image/background/1-1.png
powerhouse_assistant/GameGooseKiller/image/background/1-2.png
powerhouse_assistant/GameGooseKiller/image/background/1-3.png
powerhouse_assistant/GameGooseKiller/image/background.png
powerhouse_assistant/GameGooseKiller/image/bonus.png
powerhouse_assistant/GameGooseKiller/image/boom.png
powerhouse_assistant/GameGooseKiller/image/enemy.png
powerhouse_assistant/GameGooseKiller/image/Farm-Goose.ico
powerhouse_assistant/GameGooseKiller/image/gameover.png
powerhouse_assistant/GameGooseKiller/image/Goose/1-1.png
powerhouse_assistant/GameGooseKiller/image/Goose/1-2.png
powerhouse_assistant/GameGooseKiller/image/Goose/1-3.png
powerhouse_assistant/GameGooseKiller/image/Goose/1-4.png
powerhouse_assistant/GameGooseKiller/image/Goose/1-5.png
powerhouse_assistant/NoteBook/Note.py
powerhouse_assistant/NoteBook/Note_Book_Handler.py
powerhouse_assistant/NoteBook/note_saves/note_book.log
powerhouse_assistant/NoteBook/note_saves/note_book_auto_save.bin
powerhouse_assistant/OtherModules/Sort_Files.py
powerhouse_assistant/OtherModules/Сalculator.py
powerhouse_assistant-0.1.0.dist-info/entry_points.txt
powerhouse_assistant-0.1.0.dist-info/METADATA
powerhouse_assistant-0.1.0.dist-info/WHEEL
powerhouse_assistant-0.1.0.dist-info/RECORD
