Metadata-Version: 2.1
Name: powerhouse-assistant
Version: 0.1.0
Summary: 
Author: Your Name
Author-email: you@example.com
Requires-Python: >=3.10,<4.0
Classifier: Programming Language :: Python :: 3
Classifier: Programming Language :: Python :: 3.10
Classifier: Programming Language :: Python :: 3.11
Requires-Dist: prettytable (>=3.6.0,<4.0.0)
Requires-Dist: prompt-toolkit (>=3.0.38,<4.0.0)
Requires-Dist: pygame (>=2.3.0,<3.0.0)
